MANIFEST.in
README.md
setup.py
tf_word2vec.egg-info/PKG-INFO
tf_word2vec.egg-info/SOURCES.txt
tf_word2vec.egg-info/dependency_links.txt
tf_word2vec.egg-info/entry_points.txt
tf_word2vec.egg-info/not-zip-safe
tf_word2vec.egg-info/requires.txt
tf_word2vec.egg-info/top_level.txt
word2vec/__init__.py
word2vec/main.py
word2vec/estimators/__init__.py
word2vec/estimators/word2vec.py
word2vec/evaluation/__init__.py
word2vec/evaluation/men.py
word2vec/exceptions/__init__.py
word2vec/exceptions/method.py
word2vec/exceptions/parameter.py
word2vec/logging/__init__.py
word2vec/logging/logging.yml
word2vec/models/__init__.py
word2vec/models/word2vec.py
word2vec/resources/MEN_dataset_natural_form_full
word2vec/utils/__init__.py
word2vec/utils/config.py
word2vec/utils/datasets.py
word2vec/utils/files.py
word2vec/utils/immutables.py
word2vec/utils/vocab.py