Metadata-Version: 2.1
Name: tf-word2vec
Version: 1.0.4
Summary: Word2Vec implentation with Tensorflow Estimators and Datasets
Home-page: https://github.com/akb89/word2vec
Author:  Alexandre Kabbach
Author-email: akb@3azouz.net
License: MIT
Download-URL: https://github.com/akb89/word2vec/archive/1.0.3.tar.gz
Keywords: word2vec,word embeddings,tensorflow,estimators,datasets
Platform: any
Classifier: Development Status :: 5 - Production/Stable
Classifier: Intended Audience :: Developers
Classifier: Intended Audience :: Education
Classifier: Intended Audience :: Science/Research
Classifier: License :: OSI Approved :: MIT License
Classifier: Natural Language :: English
Classifier: Operating System :: OS Independent
Classifier: Programming Language :: Python :: 3.6
Classifier: Programming Language :: Python :: 3.7
Classifier: Topic :: Scientific/Engineering :: Artificial Intelligence
Classifier: Topic :: Software Development :: Libraries :: Python Modules
Classifier: Topic :: Text Processing :: Linguistic
